tcCalculator.py
tccalculator-0.1.0.dist-info/LICENSE
tccalculator-0.1.0.dist-info/WHEEL
tccalculator-0.1.0.dist-info/METADATA
tccalculator-0.1.0.dist-info/RECORD
