Metadata-Version: 2.1
Name: tcCalculator
Version: 0.1.0
Summary: Simple math calculator with memory. Includes nth root calculation.
Author-email: Daraab <daraabpathania@hotmail.com>
Classifier: License :: OSI Approved :: MIT License
